grad_descent_visualizer/__init__.py
grad_descent_visualizer/descent.py
grad_descent_visualizer/plotting.py
grad_descent_visualizer/test_functions.py
grad_descent_visualizer-0.1.1.dist-info/LICENSE
grad_descent_visualizer-0.1.1.dist-info/METADATA
grad_descent_visualizer-0.1.1.dist-info/WHEEL
grad_descent_visualizer-0.1.1.dist-info/top_level.txt
grad_descent_visualizer-0.1.1.dist-info/RECORD
