Metadata-Version: 2.1
Name: grad-descent-visualizer
Version: 0.1.1
Summary: A package for visualizing test functions and gradient descent.
Author: Jacob Bumgarner
License: GPLv3+
Project-URL: GitHub, https://github.com/JacobBumgarner/grad-descent-visualizer
Classifier: Programming Language :: Python :: 3
Classifier: License :: OSI Approved :: GNU General Public License v3 or later (GPLv3+)
Classifier: Operating System :: OS Independent
Requires-Python: >=3.7
License-File: LICENSE
Requires-Dist: autograd (==1.4)
Requires-Dist: numpy (==1.22.4)
Requires-Dist: pyvista (==0.35.1)
Requires-Dist: cmocean (==2.0)
Requires-Dist: colorcet (==3.0.0)
